{
  "multipart": [
    {
      "when": {
        "facing": "down"
      },
      "apply": {
        "model": "spectralization:block/photodetector"
      }
    },
    {
      "when": {
        "facing": "up"
      },
      "apply": {
        "model": "spectralization:block/photodetector",
        "x": 180
      }
    },
    {
      "when": {
        "facing": "north"
      },
      "apply": {
        "model": "spectralization:block/photodetector",
        "x": 90,
        "y": 180
      }
    },
    {
      "when": {
        "facing": "east"
      },
      "apply": {
        "model": "spectralization:block/photodetector",
        "x": 90,
        "y": 270
      }
    },
    {
      "when": {
        "facing": "south"
      },
      "apply": {
        "model": "spectralization:block/photodetector",
        "x": 90
      }
    },
    {
      "when": {
        "facing": "west"
      },
      "apply": {
        "model": "spectralization:block/photodetector",
        "x": 90,
        "y": 90
      }
    }
  ]
}
